simplegallery_bulkcreation/__init__.py
simplegallery_bulkcreation/core.py
simplegallery_bulkcreation/galleryclass.py
simplegallery_bulkcreation/utils.py
simplegallery_bulkcreation/data/public/css/default-skin.css
simplegallery_bulkcreation/data/public/css/main.css
simplegallery_bulkcreation/data/templates/galleryoverview_macros.jinja
simplegallery_bulkcreation/data/templates/index_template.jinja
simple_photo_gallery_bulkcreation-0.2.0.dist-info/LICENSE
simple_photo_gallery_bulkcreation-0.2.0.dist-info/METADATA
simple_photo_gallery_bulkcreation-0.2.0.dist-info/WHEEL
simple_photo_gallery_bulkcreation-0.2.0.dist-info/entry_points.txt
simple_photo_gallery_bulkcreation-0.2.0.dist-info/top_level.txt
simple_photo_gallery_bulkcreation-0.2.0.dist-info/RECORD
