Metadata-Version: 2.1
Name: simple-photo-gallery-bulkcreation
Version: 0.2.0
Summary: Plugin for the simple-photo-gallery to provide a config based bulk creation
Home-page: https://github.com/hille721/simple-photo-gallery-bulkcreation/
Author: Christoph Hille
Author-email: hille721@gmail.com
License: MIT License
Project-URL: Documentation, https://github.com/hille721/simple-photo-gallery-bulkcreation/
Platform: any
Classifier: Development Status :: 5 - Production/Stable
Classifier: Programming Language :: Python
Classifier: Programming Language :: Python :: 3
Classifier: Programming Language :: Python :: 3.6
Classifier: Programming Language :: Python :: 3.7
Classifier: Programming Language :: Python :: 3.8
Classifier: Programming Language :: Python :: 3.9
Classifier: Operating System :: POSIX :: Linux
Classifier: Operating System :: MacOS
Classifier: Operating System :: Microsoft :: Windows
Classifier: License :: OSI Approved :: MIT License
License-File: LICENSE
Requires-Dist: simple-photo-gallery (==1.5.*)
Requires-Dist: Jinja2
